{
  "site": {
    "title": "SlashWrite",
    "description": "Personal portfolio site blending blog posts, professional work, and creative hobbies",
    "url": "https://tannisanta.github.io/slashwrite/",
    "author": "Tetiana Tsakun",
    "location": "Warsaw, Poland",
    "email": "tannisanta@gmail.com",
    "logo": "/logo.svg",
    "homeTitle": "SlashWrite",
    "homeSubtitle": "Welcome to my space, where I explore technical writing alongside my creative hobbies. The site title reflects the effort behind every piece of content and what technical writers do — investigate, gather information, analyze, test, question, and connect the dots before writing.",
    "blogSubtitle": "Insights, experiences, and knowledge sharing on technology, learning, creativity, and everything in between",
    "projectSubtitle": "A curated showcase of my personal projects, writing, thoughts, work, and creativity",
    "canvasSubtitle": "Here I share my creative journey that inspires me and helps me keep the creative spark glowing",
    "brandTitle": "Tetiana Tsakun"
  },
  "giscus": {
    "enabled": true,
    "repo": "slashwrite",
    "repoId": "R_kgDOO_1i3A",
    "category": "General",
    "categoryId": "DIC_kwDOOl9Jt84Cp3pA",
    "mapping": "pathname",
    "strict": "0",
    "theme": "preferred_color_scheme",
    "reactionsEnabled": true,
    "emitMetadata": false,
    "inputPosition": "top",
    "lang": "en",
    "loading": "lazy"
  },
  "seo": {
    "openGraph": {
      "defaultImageWidth": 1200,
      "defaultImageHeight": 630
    },
    "analytics": {
      "googleAnalyticsId": "",
      "baiduAnalyticsId": ""
    }
  },
  "social": {
    "github": "https://github.com/tannisanta",
    "linkedin": "https://www.linkedin.com/in/tetiana-tsakun/"
  },
  "features": {
    "darkMode": true,
    "tableOfContents": true,
    "readingTime": true,
    "search": true,
    "comments": true
  }
} 